lmpc/__init__.py
lmpc/juliapkg.json
lmpc/lmpc.py
lmpc/plot.jl
lmpc-0.4.1.dist-info/METADATA
lmpc-0.4.1.dist-info/WHEEL
lmpc-0.4.1.dist-info/licenses/LICENSE
lmpc-0.4.1.dist-info/RECORD
