Metadata-Version: 2.4
Name: lmpc
Version: 0.4.1
Summary: A Python package for Linear Model Predictive Control, with generation of high-performant and embeddable code.
Project-URL: Homepage, https://github.com/darnstrom/lmpc
Project-URL: Issues, https://github.com/darnstrom/lmpc/issues
Author-email: Daniel Arnström <daniel.arnstrom@gmail.com>
License-File: LICENSE
Requires-Python: >=3.9
Requires-Dist: juliacall>=0.9.26
Requires-Dist: numpy
